scraprom/__init__.py
scraprom/collector.py
scraprom/defaults.py
scraprom-1.0.2.dist-info/LICENSE
scraprom-1.0.2.dist-info/METADATA
scraprom-1.0.2.dist-info/WHEEL
scraprom-1.0.2.dist-info/top_level.txt
scraprom-1.0.2.dist-info/RECORD
