Metadata-Version: 2.1
Name: scraprom
Version: 1.0.2
Summary: Scrapy stats collector for prometheus
Home-page: https://github.com/netflame/scraprom
Author: ilpan
Author-email: pna.dev@outlook.com
License: MIT
Keywords: scrapy prometheus exporter
Platform: UNKNOWN
Classifier: Development Status :: 3 - Alpha
Classifier: Framework :: Scrapy
Classifier: Intended Audience :: Developers
Classifier: License :: OSI Approved :: MIT License
Classifier: Operating System :: OS Independent
Classifier: Programming Language :: Python
Classifier: Programming Language :: Python :: 3
Classifier: Programming Language :: Python :: 3.7
Classifier: Topic :: Internet :: WWW/HTTP
Requires-Python: >=3
Requires-Dist: prometheus-client
Requires-Dist: scrapy
